[
    {
        "id": "file-mE5xSbyx1XYSYYoMduo5upLC",
        "bytes": 1554831,
        "created_at": 1700098823,
        "filename": "theory_of_justice.pdf",
        "object": "file",
        "purpose": "assistants",
        "status": "processed",
        "status_details": null
    },
    {
        "id": "file-7VF1V4utGyL8mdMreGk8fG18",
        "bytes": 1454681,
        "created_at": 1700098824,
        "filename": "law_of_peoples.pdf",
        "object": "file",
        "purpose": "assistants",
        "status": "processed",
        "status_details": null
    },
    {
        "id": "file-DVy2OlQXw7uASeNkVuujoelt",
        "bytes": 3150430,
        "created_at": 1700098826,
        "filename": "public_reason_revisited.pdf",
        "object": "file",
        "purpose": "assistants",
        "status": "processed",
        "status_details": null
    },
    {
        "id": "file-gYuhKAkWb0WetQqeUgxNXK9G",
        "bytes": 1888266,
        "created_at": 1700098828,
        "filename": "history_moral_philosophy.pdf",
        "object": "file",
        "purpose": "assistants",
        "status": "processed",
        "status_details": null
    },
    {
        "id": "file-ceDvlXqzrKlDafLRv1IS7Z0K",
        "bytes": 2614882,
        "created_at": 1700098830,
        "filename": "justice_as_fairness_intro.pdf",
        "object": "file",
        "purpose": "assistants",
        "status": "processed",
        "status_details": null
    },
    {
        "id": "file-mE5xSbyx1XYSYYoMduo5upLC",
        "bytes": 532412,
        "created_at": 1700098832,
        "filename": "encyclopedias.txt",
        "object": "file",
        "purpose": "assistants",
        "status": "processed",
        "status_details": null
    }
]
